k1lib/__init__.py
k1lib/_advanced.py
k1lib/_baseClasses.py
k1lib/_basics.py
k1lib/_context.py
k1lib/_higher.py
k1lib/_k1a.py
k1lib/_learner.py
k1lib/_monkey.py
k1lib/_perlin.py
k1lib/assets.py
k1lib/eqn.py
k1lib/fmt.py
k1lib/graphEqn.py
k1lib/imports.py
k1lib/kast.py
k1lib/kcom.py
k1lib/kgis.py
k1lib/knn.py
k1lib/kop.py
k1lib/kph.py
k1lib/kstr.py
k1lib/kws.py
k1lib/p5.py
k1lib/pw_top100k_bloom.bin
k1lib/schedule.py
k1lib/selector.py
k1lib/selen.py
k1lib/serpent.py
k1lib/trans.py
k1lib/viz.py
k1lib/web.py
k1lib/zircon.py
k1lib/_hidden/__init__.py
k1lib/_hidden/hiddenFile.py
k1lib/_mo/__init__.py
k1lib/_mo/atom.py
k1lib/_mo/parseM.py
k1lib/_mo/substance.py
k1lib/_mo/system.py
k1lib/assets/acorn.js
k1lib/assets/acorn_walk.js
k1lib/assets/chartist.css
k1lib/assets/chartist.js
k1lib/assets/k1js_amd.js
k1lib/assets/k1js_umd.js
k1lib/assets/leaflet.css
k1lib/assets/leaflet.js
k1lib/callbacks/__init__.py
k1lib/callbacks/callbacks.py
k1lib/callbacks/confusionMatrix.py
k1lib/callbacks/core.py
k1lib/callbacks/hookModule.py
k1lib/callbacks/hookParam.py
k1lib/callbacks/landscape.py
k1lib/callbacks/limits.py
k1lib/callbacks/loss_accuracy.py
k1lib/callbacks/paramFinder.py
k1lib/callbacks/profiler.py
k1lib/callbacks/progress.py
k1lib/callbacks/recorder.py
k1lib/callbacks/shorts.py
k1lib/callbacks/lossFunctions/__init__.py
k1lib/callbacks/lossFunctions/accuracy.py
k1lib/callbacks/lossFunctions/shorts.py
k1lib/callbacks/profilers/__init__.py
k1lib/callbacks/profilers/computation.py
k1lib/callbacks/profilers/io.py
k1lib/callbacks/profilers/memory.py
k1lib/callbacks/profilers/time.py
k1lib/cli/__init__.py
k1lib/cli/_applyCl.py
k1lib/cli/bio.py
k1lib/cli/cif.py
k1lib/cli/conv.py
k1lib/cli/filt.py
k1lib/cli/gb.py
k1lib/cli/grep.py
k1lib/cli/init.py
k1lib/cli/inp.py
k1lib/cli/kapi.py
k1lib/cli/kcv.py
k1lib/cli/kgv.py
k1lib/cli/kjs.py
k1lib/cli/ktree.py
k1lib/cli/kxml.py
k1lib/cli/lsext.py
k1lib/cli/mgi.py
k1lib/cli/models.py
k1lib/cli/modifier.py
k1lib/cli/mol.py
k1lib/cli/nb.py
k1lib-1.8.1.dist-info/LICENSE
k1lib-1.8.1.dist-info/METADATA
k1lib-1.8.1.dist-info/WHEEL
k1lib-1.8.1.dist-info/top_level.txt
k1lib-1.8.1.dist-info/RECORD
