Metadata-Version: 2.1
Name: k1lib
Version: 1.8.1
Summary: Some nice ML overhaul
Home-page: https://k1lib.com
Author: Quang Ho
Author-email: 157239q@gmail.com
License: MIT
Requires-Python: >=3.7
License-File: LICENSE
Requires-Dist: numpy>=1.14
Requires-Dist: matplotlib>=2.0
Requires-Dist: dill
Requires-Dist: forbiddenfruit
Requires-Dist: wurlitzer
Requires-Dist: validators
Provides-Extra: all
Requires-Dist: graphviz; extra == "all"
Requires-Dist: torchvision; extra == "all"
Requires-Dist: pillow; extra == "all"
Requires-Dist: scikit-image; extra == "all"
Requires-Dist: pyperclip; extra == "all"
Requires-Dist: k1a<2,>=1.2; extra == "all"
Requires-Dist: torch; extra == "all"
